deepctl_cmd_debug_browser/__init__.py
deepctl_cmd_debug_browser/command.py
deepctl_cmd_debug_browser/models.py
deepctl_cmd_debug_browser/static/__init__.py
deepctl_cmd_debug_browser/static/debug.html
deepctl_cmd_debug_browser-0.1.10.dist-info/METADATA
deepctl_cmd_debug_browser-0.1.10.dist-info/WHEEL
deepctl_cmd_debug_browser-0.1.10.dist-info/entry_points.txt
deepctl_cmd_debug_browser-0.1.10.dist-info/top_level.txt
deepctl_cmd_debug_browser-0.1.10.dist-info/RECORD
